invariant_sdk/__init__.py
invariant_sdk/async_client.py
invariant_sdk/base_client.py
invariant_sdk/client.py
invariant_sdk/types/annotations.py
invariant_sdk/types/append_messages.py
invariant_sdk/types/exceptions.py
invariant_sdk/types/push_traces.py
invariant_sdk/types/update_dataset_metadata.py
invariant_sdk/utils.py
invariant_sdk-0.0.11.dist-info/METADATA
invariant_sdk-0.0.11.dist-info/WHEEL
invariant_sdk-0.0.11.dist-info/RECORD
